gconnectdb/__init__.py
gconnectdb/config.py
gconnectdb/ssh_tunnel.py
test/__init__.py
test/test_ssh_tunnel.py
GConnectDB-0.1.2.dist-info/METADATA
GConnectDB-0.1.2.dist-info/WHEEL
GConnectDB-0.1.2.dist-info/top_level.txt
GConnectDB-0.1.2.dist-info/RECORD
